README.txt
setup.py
rpc_proxy.egg-info/PKG-INFO
rpc_proxy.egg-info/SOURCES.txt
rpc_proxy.egg-info/dependency_links.txt
rpc_proxy.egg-info/not-zip-safe
rpc_proxy.egg-info/top_level.txt
rpc_thrift/__init__.py
rpc_thrift/config.py
rpc_thrift/heartbeat.py
rpc_thrift/pool.py
rpc_thrift/protocol.py
rpc_thrift/rpc_wrapper.py
rpc_thrift/server.py
rpc_thrift/socket_buffer.py
rpc_thrift/transport.py
rpc_thrift/utils.py
rpc_thrift/worker.py
rpc_thrift/cython/__init__.py
rpc_thrift/cython/cybase.pxd
rpc_thrift/cython/cybase.pyx
rpc_thrift/cython/cybinary_protocol.pyx
rpc_thrift/cython/cyframed_transport.pxd
rpc_thrift/cython/cyframed_transport.pyx
rpc_thrift/cython/cyframed_transport_ex.pxd
rpc_thrift/cython/cyframed_transport_ex.pyx
rpc_thrift/cython/cymemory_transport.pxd
rpc_thrift/cython/cymemory_transport.pyx
rpc_thrift/log_utils/__init__.py
rpc_thrift/log_utils/log.py
rpc_thrift/log_utils/log_handlers.py
rpc_thrift/log_utils/loggers.py
rpc_thrift/services/RpcServiceBase.py
rpc_thrift/services/__init__.py
rpc_thrift/services/constants.py
rpc_thrift/services/ttypes.py
test/test_framed_buffer.py
test/test_protocol.py